py_sc_fermi/__init__.py
py_sc_fermi/defect_charge_state.py
py_sc_fermi/defect_species.py
py_sc_fermi/defect_system.py
py_sc_fermi/dos.py
py_sc_fermi/inputs.py
py_sc_fermi/cli/__init__.py
py_sc_fermi/cli/sc_fermi_solve.py
py_sc_fermi-2.0.4.dist-info/LICENSE
py_sc_fermi-2.0.4.dist-info/METADATA
py_sc_fermi-2.0.4.dist-info/WHEEL
py_sc_fermi-2.0.4.dist-info/entry_points.txt
py_sc_fermi-2.0.4.dist-info/top_level.txt
py_sc_fermi-2.0.4.dist-info/RECORD
