Metadata-Version: 2.2
Name: py_sc_fermi
Version: 2.0.4
Summary: Self-consistent Fermi Analysis
Author: Alex G. Squires
Author-email: "Benjamin J. Morgan" <b.j.morgan@bath.ac.uk>
License: MIT
Project-URL: Homepage, https://github.com/bjmorgan/py-sc-fermi
Project-URL: Download, https://github.com/bjmorgan/py-sc-fermi/archive/v{version}.tar.gz
Requires-Python: >=3.8
License-File: LICENSE
Requires-Dist: numpy
Requires-Dist: scipy
Requires-Dist: pymatgen
Requires-Dist: pyyaml
